Workbook

Sheet Dashboard
A1: FINTECH ANALYTICS PLATFORM — CredIntel
A2: Every figure below is a live formula on the datasets in this workbook (n=200 credit records, n=200 user records, both simulated).
A4: MODEL ACCURACY (TEST) | E4: TOTAL USERS | I4: REVENUE DRIVER | M4: DEFAULT RATE
A5: ='Model Performance'!B10 -> 0.93333333 | E5: ='Segment Stats'!B9 -> 200 | I5: ='Segment Stats'!H5 -> 0.53561668 | M5: =Portfolio!B7 -> 0.275
A6: Logistic regression | E6: Rule-based segments | I6: Share of spend: High Spenders | M6: Credit dataset (n=200)
A9: Credit metric | B9: Value | C9: Note | F9: Segment | G9: Users | H9: Avg Spend/mo | I9: % Share
A10: Accuracy | B10: ='Model Performance'!B10 -> 0.93333333 | C10: Hold-out test | F10: ='Segment Stats'!A5 -> High Spenders | G10: ='Segment Stats'!B5 -> 62 | H10: ='Segment Stats'!D5 -> 41432.758 | I10: ='Segment Stats'!C5 -> 0.31
A11: Precision | B11: ='Model Performance'!B11 -> 0.83333333 | C11: Default class | F11: ='Segment Stats'!A6 -> Frequent Users | G11: ='Segment Stats'!B6 -> 30 | H11: ='Segment Stats'!D6 -> 18220.067 | I11: ='Segment Stats'!C6 -> 0.15
A12: Recall | B12: ='Model Performance'!B12 -> 0.9375 | C12: Default class | F12: ='Segment Stats'!A7 -> Low Activity | G12: ='Segment Stats'!B7 -> 18 | H12: ='Segment Stats'!D7 -> 14148.111 | I12: ='Segment Stats'!C7 -> 0.09
A13: F1 | B13: ='Model Performance'!B13 -> 0.88235294 | F13: ='Segment Stats'!A8 -> Mid-Tier | G13: ='Segment Stats'!B8 -> 90 | H13: ='Segment Stats'!D8 -> 15843.622 | I13: ='Segment Stats'!C8 -> 0.45
A14: AUC-ROC | B14: ='Model Performance'!B14 -> 0.993 | C14: 60 test rows — indicative
A15: Loans | B15: =Portfolio!B4 -> 200 | F15: Active users (≥ threshold logins) | I15: =COUNTIF('Segmentation Data'!E4:E203,">="&Assumptions!B8) -> 157
A16: Total disbursed (INR) | B16: =Portfolio!B5 -> 8733027 | F16: Active % | I16: =I15/'Segment Stats'!B9 -> 0.785
A17: NPA exposure (INR) | B17: =Portfolio!B8 -> 3088982
A18: Net P&L (INR, illustrative) | B18: =Portfolio!B11 -> -2041018.8 | C18: Interest − NPA

Sheet Assumptions
A1: ASSUMPTIONS & THRESHOLDS
A2: Blue = editable input. Segment rules and portfolio P&L recalculate from these. Demo-only illustrative figures are listed at the bottom.
A4: Parameter | B4: Value | C4: Used for
A5: High Spender threshold — monthly spend (INR) ≥ | B5: 35000 | C5: Segment rule 1
A6: Frequent User threshold — login days/mo ≥ | B6: 23 | C6: Segment rule 2
A7: Low Activity threshold — txn count ≤ | B7: 9 | C7: Segment rule 3 (else Mid-Tier)
A8: Active user threshold — login days/mo ≥ | B8: 8 | C8: Active users KPI
A9: Default probability cut-off | B9: 0.5 | C9: Predicted class
A10: Loan interest rate (annual) | B10: 0.12 | C10: Portfolio interest income
A11: Funnel: visitors (illustrative) | B11: 1000 | C11: Funnel top stage
A12: Funnel: active → loan-ready rate (illustrative) | B12: 0.405 | C12: Funnel last stage
A15: DEMO-ONLY ILLUSTRATIVE FIGURES (not derived from data — shown in the demo with an "Illustrative" label)
A16: Metric | B16: Value | C16: Note
A17: CAC (INR) | B17: 840 | C17: Assumption — no source dataset
A18: LTV (INR) | B18: 22400 | C18: Assumption — no source dataset
A19: ARPU per month (INR) | B19: 1840 | C19: Assumption — no source dataset
A20: LTV:CAC ratio | B20: =B18/B17 -> 26.666667 | C20: Assumption — no source dataset
A21: Payback period (months) | B21: 5.4 | C21: Assumption — no source dataset
A22: Fintech avg default rate (benchmark) | B22: 0.126 | C22: Assumption — no source dataset
A23: Fintech avg CAC (INR) | B23: 1280 | C23: Assumption — no source dataset
A24: Fintech avg LTV (INR) | B24: 18600 | C24: Assumption — no source dataset

Sheet Credit Risk Data
A1: CREDIT RISK — DATASET (200 records, simulated)
A2: LTI is now a formula. Pred Prob = logistic regression output (trained on rows marked Train, scored on all rows).
A3: Customer ID | B3: Age | C3: Annual Income (INR) | D3: Loan Amount (INR) | E3: Credit History | F3: Employment | G3: LTI Ratio | H3: Default (1=Yes) | I3: Pred Prob | J3: Pred Class | K3: Set
A4: CUST-1001 | B4: 59 | C4: 58623 | D4: 15966 | E4: Bad | F4: Self-Employed | G4: =D4/C4 -> 0.27235044 | H4: 0 | I4: 0.0379 | J4: =IF(I4>=Assumptions!$B$9,1,0) -> 0 | K4: Train
A5: CUST-1002 | B5: 49 | C5: 27392 | D5: 57921 | E5: Good | F5: Unemployed | G5: =D5/C5 -> 2.1145225 | H5: 1 | I5: 0.9885 | J5: =IF(I5>=Assumptions!$B$9,1,0) -> 1 | K5: Train
A6: CUST-1003 | B6: 35 | C6: 75680 | D6: 54726 | E6: Good | F6: Unemployed | G6: =D6/C6 -> 0.72312368 | H6: 0 | I6: 0.1112 | J6: =IF(I6>=Assumptions!$B$9,1,0) -> 0 | K6: Test
A7: CUST-1004 | B7: 63 | C7: 66717 | D7: 55300 | E7: Average | F7: Unemployed | G7: =D7/C7 -> 0.8288742 | H7: 1 | I7: 0.5366 | J7: =IF(I7>=Assumptions!$B$9,1,0) -> 1 | K7: Train
A8: CUST-1005 | B8: 28 | C8: 107092 | D8: 27677 | E8: Average | F8: Unemployed | G8: =D8/C8 -> 0.25844134 | H8: 0 | I8: 0.0808 | J8: =IF(I8>=Assumptions!$B$9,1,0) -> 0 | K8: Test
A9: CUST-1006 | B9: 41 | C9: 70859 | D9: 60609 | E9: Average | F9: Unemployed | G9: =D9/C9 -> 0.85534653 | H9: 1 | I9: 0.6227 | J9: =IF(I9>=Assumptions!$B$9,1,0) -> 1 | K9: Train
A10: CUST-1007 | B10: 59 | C10: 46309 | D10: 61661 | E10: Good | F10: Employed | G10: =D10/C10 -> 1.3315122 | H10: 0 | I10: 0.0509 | J10: =IF(I10>=Assumptions!$B$9,1,0) -> 0 | K10: Train
A11: CUST-1008 | B11: 39 | C11: 107455 | D11: 36024 | E11: Bad | F11: Unemployed | G11: =D11/C11 -> 0.33524731 | H11: 1 | I11: 0.4398 | J11: =IF(I11>=Assumptions!$B$9,1,0) -> 0 | K11: Test
A12: CUST-1009 | B12: 43 | C12: 83734 | D12: 75313 | E12: Good | F12: Unemployed | G12: =D12/C12 -> 0.89943153 | H12: 0 | I12: 0.1764 | J12: =IF(I12>=Assumptions!$B$9,1,0) -> 0 | K12: Train
A13: CUST-1010 | B13: 31 | C13: 90467 | D13: 58006 | E13: Bad | F13: Unemployed | G13: =D13/C13 -> 0.64118408 | H13: 1 | I13: 0.8082 | J13: =IF(I13>=Assumptions!$B$9,1,0) -> 1 | K13: Train
A14: CUST-1011 | B14: 31 | C14: 72662 | D14: 20338 | E14: Good | F14: Unemployed | G14: =D14/C14 -> 0.27989871 | H14: 0 | I14: 0.0198 | J14: =IF(I14>=Assumptions!$B$9,1,0) -> 0 | K14: Train
A15: CUST-1012 | B15: 44 | C15: 118506 | D15: 73027 | E15: Bad | F15: Self-Employed | G15: =D15/C15 -> 0.6162304 | H15: 0 | I15: 0.0825 | J15: =IF(I15>=Assumptions!$B$9,1,0) -> 0 | K15: Train
... A203: CUST-1200 | B203: 57 | C203: 52097 | D203: 20485 | E203: Good | F203: Unemployed | G203: =D203/C203 -> 0.39320882 | H203: 0 | I203: 0.0303 | J203: =IF(I203>=Assumptions!$B$9,1,0) -> 0 | K203: Train

Sheet Segmentation Data
A1: CUSTOMER SEGMENTATION — DATASET (200 records, simulated)
A2: Avg Txn Value = Spend ÷ Txn Count. Segment is a rule driven by Assumptions thresholds.
A3: User ID | B3: Monthly Spend (INR) | C3: Txn Count | D3: Avg Txn Value (INR) | E3: Login Days/mo | F3: Wallet Balance (INR) | G3: Months Active | H3: Segment
A4: USR-2001 | B4: 28034 | C4: 20 | D4: =B4/C4 -> 1401.7 | E4: 2 | F4: 73972 | G4: 27 | H4: =IF(B4>=Assumptions!$B$5,"High Spenders",IF(E4>=Assumptions!$B$6,"Frequent Users",IF(C4<=Assumptions!$B$7,"Low Activity","Mid-Tier"))) -> Mid-Tier
A5: USR-2002 | B5: 14731 | C5: 41 | D5: =B5/C5 -> 359.29268 | E5: 12 | F5: 62187 | G5: 17 | H5: =IF(B5>=Assumptions!$B$5,"High Spenders",IF(E5>=Assumptions!$B$6,"Frequent Users",IF(C5<=Assumptions!$B$7,"Low Activity","Mid-Tier"))) -> Mid-Tier
A6: USR-2003 | B6: 32793 | C6: 49 | D6: =B6/C6 -> 669.2449 | E6: 13 | F6: 12984 | G6: 12 | H6: =IF(B6>=Assumptions!$B$5,"High Spenders",IF(E6>=Assumptions!$B$6,"Frequent Users",IF(C6<=Assumptions!$B$7,"Low Activity","Mid-Tier"))) -> Mid-Tier
A7: USR-2004 | B7: 27114 | C7: 20 | D7: =B7/C7 -> 1355.7 | E7: 25 | F7: 33039 | G7: 22 | H7: =IF(B7>=Assumptions!$B$5,"High Spenders",IF(E7>=Assumptions!$B$6,"Frequent Users",IF(C7<=Assumptions!$B$7,"Low Activity","Mid-Tier"))) -> Frequent Users
A8: USR-2005 | B8: 36758 | C8: 54 | D8: =B8/C8 -> 680.7037 | E8: 21 | F8: 85431 | G8: 17 | H8: =IF(B8>=Assumptions!$B$5,"High Spenders",IF(E8>=Assumptions!$B$6,"Frequent Users",IF(C8<=Assumptions!$B$7,"Low Activity","Mid-Tier"))) -> High Spenders
A9: USR-2006 | B9: 28753 | C9: 22 | D9: =B9/C9 -> 1306.9545 | E9: 7 | F9: 83691 | G9: 10 | H9: =IF(B9>=Assumptions!$B$5,"High Spenders",IF(E9>=Assumptions!$B$6,"Frequent Users",IF(C9<=Assumptions!$B$7,"Low Activity","Mid-Tier"))) -> Mid-Tier
A10: USR-2007 | B10: 42578 | C10: 28 | D10: =B10/C10 -> 1520.6429 | E10: 10 | F10: 58606 | G10: 1 | H10: =IF(B10>=Assumptions!$B$5,"High Spenders",IF(E10>=Assumptions!$B$6,"Frequent Users",IF(C10<=Assumptions!$B$7,"Low Activity","Mid-Tier"))) -> High Spenders
A11: USR-2008 | B11: 41252 | C11: 40 | D11: =B11/C11 -> 1031.3 | E11: 13 | F11: 10616 | G11: 22 | H11: =IF(B11>=Assumptions!$B$5,"High Spenders",IF(E11>=Assumptions!$B$6,"Frequent Users",IF(C11<=Assumptions!$B$7,"Low Activity","Mid-Tier"))) -> High Spenders
A12: USR-2009 | B12: 18488 | C12: 49 | D12: =B12/C12 -> 377.30612 | E12: 17 | F12: 50072 | G12: 26 | H12: =IF(B12>=Assumptions!$B$5,"High Spenders",IF(E12>=Assumptions!$B$6,"Frequent Users",IF(C12<=Assumptions!$B$7,"Low Activity","Mid-Tier"))) -> Mid-Tier
A13: USR-2010 | B13: 31537 | C13: 7 | D13: =B13/C13 -> 4505.2857 | E13: 26 | F13: 24574 | G13: 18 | H13: =IF(B13>=Assumptions!$B$5,"High Spenders",IF(E13>=Assumptions!$B$6,"Frequent Users",IF(C13<=Assumptions!$B$7,"Low Activity","Mid-Tier"))) -> Frequent Users
A14: USR-2011 | B14: 12719 | C14: 1 | D14: =B14/C14 -> 12719 | E14: 21 | F14: 3430 | G14: 14 | H14: =IF(B14>=Assumptions!$B$5,"High Spenders",IF(E14>=Assumptions!$B$6,"Frequent Users",IF(C14<=Assumptions!$B$7,"Low Activity","Mid-Tier"))) -> Low Activity
A15: USR-2012 | B15: 735 | C15: 32 | D15: =B15/C15 -> 22.96875 | E15: 28 | F15: 12676 | G15: 29 | H15: =IF(B15>=Assumptions!$B$5,"High Spenders",IF(E15>=Assumptions!$B$6,"Frequent Users",IF(C15<=Assumptions!$B$7,"Low Activity","Mid-Tier"))) -> Frequent Users
... A203: USR-2200 | B203: 5444 | C203: 40 | D203: =B203/C203 -> 136.1 | E203: 29 | F203: 7491 | G203: 21 | H203: =IF(B203>=Assumptions!$B$5,"High Spenders",IF(E203>=Assumptions!$B$6,"Frequent Users",IF(C203<=Assumptions!$B$7,"Low Activity","Mid-Tier"))) -> Frequent Users

Sheet Segment Stats
A1: SEGMENT SUMMARY STATISTICS
A4: Segment | B4: Users | C4: % Share | D4: Avg Spend/mo | E4: Avg Txns | F4: Avg Logins | G4: Avg Balance | H4: Spend Share | I4: Churn Risk
A5: High Spenders | B5: =COUNTIF('Segmentation Data'!$H$4:$H$203,A5) -> 62 | C5: =B5/$B$9 -> 0.31 | D5: =AVERAGEIF('Segmentation Data'!$H$4:$H$203,$A5,'Segmentation Data'!$B$4:$B$203) -> 41432.758 | E5: =AVERAGEIF('Segmentation Data'!$H$4:$H$203,$A5,'Segmentation Data'!$C$4:$C$203) -> 32.016129 | F5: =AVERAGEIF('Segmentation Data'!$H$4:$H$203,$A5,'Segmentation Data'!$E$4:$E$203) -> 17.209677 | G5: =AVERAGEIF('Segmentation Data'!$H$4:$H$203,$A5,'Segmentation Data'!$F$4:$F$203) -> 51319.435 | H5: =SUMIF('Segmentation Data'!$H$4:$H$203,A5,'Segmentation Data'!$B$4:$B$203)/SUM('Segmentation Data'!$B$4:$B$203) -> 0.53561668 | I5: =IF(F5<=10,"High",IF(F5<=18,"Medium","Low")) -> Medium
A6: Frequent Users | B6: =COUNTIF('Segmentation Data'!$H$4:$H$203,A6) -> 30 | C6: =B6/$B$9 -> 0.15 | D6: =AVERAGEIF('Segmentation Data'!$H$4:$H$203,$A6,'Segmentation Data'!$B$4:$B$203) -> 18220.067 | E6: =AVERAGEIF('Segmentation Data'!$H$4:$H$203,$A6,'Segmentation Data'!$C$4:$C$203) -> 26.1 | F6: =AVERAGEIF('Segmentation Data'!$H$4:$H$203,$A6,'Segmentation Data'!$E$4:$E$203) -> 25.966667 | G6: =AVERAGEIF('Segmentation Data'!$H$4:$H$203,$A6,'Segmentation Data'!$F$4:$F$203) -> 42937.5 | H6: =SUMIF('Segmentation Data'!$H$4:$H$203,A6,'Segmentation Data'!$B$4:$B$203)/SUM('Segmentation Data'!$B$4:$B$203) -> 0.1139698 | I6: =IF(F6<=10,"High",IF(F6<=18,"Medium","Low")) -> Low
A7: Low Activity | B7: =COUNTIF('Segmentation Data'!$H$4:$H$203,A7) -> 18 | C7: =B7/$B$9 -> 0.09 | D7: =AVERAGEIF('Segmentation Data'!$H$4:$H$203,$A7,'Segmentation Data'!$B$4:$B$203) -> 14148.111 | E7: =AVERAGEIF('Segmentation Data'!$H$4:$H$203,$A7,'Segmentation Data'!$C$4:$C$203) -> 4.7222222 | F7: =AVERAGEIF('Segmentation Data'!$H$4:$H$203,$A7,'Segmentation Data'!$E$4:$E$203) -> 12.277778 | G7: =AVERAGEIF('Segmentation Data'!$H$4:$H$203,$A7,'Segmentation Data'!$F$4:$F$203) -> 54126.444 | H7: =SUMIF('Segmentation Data'!$H$4:$H$203,A7,'Segmentation Data'!$B$4:$B$203)/SUM('Segmentation Data'!$B$4:$B$203) -> 0.05309939 | I7: =IF(F7<=10,"High",IF(F7<=18,"Medium","Low")) -> Medium
A8: Mid-Tier | B8: =COUNTIF('Segmentation Data'!$H$4:$H$203,A8) -> 90 | C8: =B8/$B$9 -> 0.45 | D8: =AVERAGEIF('Segmentation Data'!$H$4:$H$203,$A8,'Segmentation Data'!$B$4:$B$203) -> 15843.622 | E8: =AVERAGEIF('Segmentation Data'!$H$4:$H$203,$A8,'Segmentation Data'!$C$4:$C$203) -> 35.244444 | F8: =AVERAGEIF('Segmentation Data'!$H$4:$H$203,$A8,'Segmentation Data'!$E$4:$E$203) -> 11.066667 | G8: =AVERAGEIF('Segmentation Data'!$H$4:$H$203,$A8,'Segmentation Data'!$F$4:$F$203) -> 51460.544 | H8: =SUMIF('Segmentation Data'!$H$4:$H$203,A8,'Segmentation Data'!$B$4:$B$203)/SUM('Segmentation Data'!$B$4:$B$203) -> 0.29731413 | I8: =IF(F8<=10,"High",IF(F8<=18,"Medium","Low")) -> Medium
A9: TOTAL | B9: =SUM(B5:B8) -> 200 | C9: =SUM(C5:C8) -> 1 | H9: =SUM(H5:H8) -> 1
A11: K-MEANS CROSS-CHECK (standardised spend, txns, logins, balance, months active; Python/scikit-learn)
A12: K | B12: Silhouette | C12: Inertia
A13: 2 | B13: 0.162 | C13: 825
A14: 3 | B14: 0.159 | C14: 721
A15: 4 | B15: 0.161 | C15: 635
A16: 5 | B16: 0.166 | C16: 570
A17: 6 | B17: 0.173 | C17: 516
A18: 7 | B18: 0.179 | C18: 479
A19: 8 | B19: 0.187 | C19: 445
A21: Finding: silhouette stays ≈0.16–0.19 for every K, so K-Means finds no strong natural clusters in this data. Segments therefore use explainable threshold rules.

Sheet Risk Analysis
A1: CREDIT RISK ANALYSIS — DEFAULT RATE BREAKDOWN
A4: DEFAULT RATE BY CREDIT HISTORY
A5: Credit History | B5: Total Borrowers | C5: Defaults | D5: Default Rate
A6: Good | B6: =COUNTIF('Credit Risk Data'!$E$4:$E$203,A6) -> 80 | C6: =COUNTIFS('Credit Risk Data'!$E$4:$E$203,A6,'Credit Risk Data'!$H$4:$H$203,1) -> 8 | D6: =C6/B6 -> 0.1
A7: Average | B7: =COUNTIF('Credit Risk Data'!$E$4:$E$203,A7) -> 66 | C7: =COUNTIFS('Credit Risk Data'!$E$4:$E$203,A7,'Credit Risk Data'!$H$4:$H$203,1) -> 21 | D7: =C7/B7 -> 0.31818182
A8: Bad | B8: =COUNTIF('Credit Risk Data'!$E$4:$E$203,A8) -> 54 | C8: =COUNTIFS('Credit Risk Data'!$E$4:$E$203,A8,'Credit Risk Data'!$H$4:$H$203,1) -> 26 | D8: =C8/B8 -> 0.48148148
A10: DEFAULT RATE BY EMPLOYMENT
A11: Employment | B11: Total Borrowers | C11: Defaults | D11: Default Rate
A12: Employed | B12: =COUNTIF('Credit Risk Data'!$F$4:$F$203,A12) -> 61 | C12: =COUNTIFS('Credit Risk Data'!$F$4:$F$203,A12,'Credit Risk Data'!$H$4:$H$203,1) -> 6 | D12: =C12/B12 -> 0.098360656
A13: Self-Employed | B13: =COUNTIF('Credit Risk Data'!$F$4:$F$203,A13) -> 70 | C13: =COUNTIFS('Credit Risk Data'!$F$4:$F$203,A13,'Credit Risk Data'!$H$4:$H$203,1) -> 15 | D13: =C13/B13 -> 0.21428571
A14: Unemployed | B14: =COUNTIF('Credit Risk Data'!$F$4:$F$203,A14) -> 69 | C14: =COUNTIFS('Credit Risk Data'!$F$4:$F$203,A14,'Credit Risk Data'!$H$4:$H$203,1) -> 34 | D14: =C14/B14 -> 0.49275362
A16: DEFAULT RATE BY ANNUAL INCOME (INR)
A17: Income Bracket | B17: Total Borrowers | C17: Defaults | D17: Default Rate
A18: 20,000–29,999 | B18: =COUNTIFS('Credit Risk Data'!$C$4:$C$203,">=20000",'Credit Risk Data'!$C$4:$C$203,"<30000") -> 27 | C18: =COUNTIFS('Credit Risk Data'!$C$4:$C$203,">=20000",'Credit Risk Data'!$C$4:$C$203,"<30000",'Credit Risk Data'!$H$4:$H$203,1) -> 19 | D18: =C18/B18 -> 0.7037037
A19: 30,000–44,999 | B19: =COUNTIFS('Credit Risk Data'!$C$4:$C$203,">=30000",'Credit Risk Data'!$C$4:$C$203,"<45000") -> 28 | C19: =COUNTIFS('Credit Risk Data'!$C$4:$C$203,">=30000",'Credit Risk Data'!$C$4:$C$203,"<45000",'Credit Risk Data'!$H$4:$H$203,1) -> 15 | D19: =C19/B19 -> 0.53571429
A20: 45,000–59,999 | B20: =COUNTIFS('Credit Risk Data'!$C$4:$C$203,">=45000",'Credit Risk Data'!$C$4:$C$203,"<60000") -> 29 | C20: =COUNTIFS('Credit Risk Data'!$C$4:$C$203,">=45000",'Credit Risk Data'!$C$4:$C$203,"<60000",'Credit Risk Data'!$H$4:$H$203,1) -> 8 | D20: =C20/B20 -> 0.27586207
A21: 60,000–79,999 | B21: =COUNTIFS('Credit Risk Data'!$C$4:$C$203,">=60000",'Credit Risk Data'!$C$4:$C$203,"<80000") -> 45 | C21: =COUNTIFS('Credit Risk Data'!$C$4:$C$203,">=60000",'Credit Risk Data'!$C$4:$C$203,"<80000",'Credit Risk Data'!$H$4:$H$203,1) -> 8 | D21: =C21/B21 -> 0.17777778
A22: 80,000+ | B22: =COUNTIFS('Credit Risk Data'!$C$4:$C$203,">=80000",'Credit Risk Data'!$C$4:$C$203,"<1000000000") -> 71 | C22: =COUNTIFS('Credit Risk Data'!$C$4:$C$203,">=80000",'Credit Risk Data'!$C$4:$C$203,"<1000000000",'Credit Risk Data'!$H$4:$H$203,1) -> 5 | D22: =C22/B22 -> 0.070422535
A24: DEFAULT RATE BY LOAN-TO-INCOME
A25: LTI Band | B25: Total Borrowers | C25: Defaults | D25: Default Rate
A26: LTI < 0.8 | B26: =COUNTIFS('Credit Risk Data'!$G$4:$G$203,">=0",'Credit Risk Data'!$G$4:$G$203,"<0.8") -> 127 | C26: =COUNTIFS('Credit Risk Data'!$G$4:$G$203,">=0",'Credit Risk Data'!$G$4:$G$203,"<0.8",'Credit Risk Data'!$H$4:$H$203,1) -> 9 | D26: =C26/B26 -> 0.070866142
A27: LTI 0.8–1.5 | B27: =COUNTIFS('Credit Risk Data'!$G$4:$G$203,">=0.8",'Credit Risk Data'!$G$4:$G$203,"<1.5") -> 46 | C27: =COUNTIFS('Credit Risk Data'!$G$4:$G$203,">=0.8",'Credit Risk Data'!$G$4:$G$203,"<1.5",'Credit Risk Data'!$H$4:$H$203,1) -> 19 | D27: =C27/B27 -> 0.41304348
A28: LTI 1.5–2.0 | B28: =COUNTIFS('Credit Risk Data'!$G$4:$G$203,">=1.5",'Credit Risk Data'!$G$4:$G$203,"<2.0") -> 12 | C28: =COUNTIFS('Credit Risk Data'!$G$4:$G$203,">=1.5",'Credit Risk Data'!$G$4:$G$203,"<2.0",'Credit Risk Data'!$H$4:$H$203,1) -> 12 | D28: =C28/B28 -> 1
A29: LTI > 2.0 | B29: =COUNTIFS('Credit Risk Data'!$G$4:$G$203,">=2.0",'Credit Risk Data'!$G$4:$G$203,"<99") -> 15 | C29: =COUNTIFS('Credit Risk Data'!$G$4:$G$203,">=2.0",'Credit Risk Data'!$G$4:$G$203,"<99",'Credit Risk Data'!$H$4:$H$203,1) -> 15 | D29: =C29/B29 -> 1
A31: FEATURE IMPORTANCE — share of absolute standardised coefficients (Python)
A32: Feature | B32: Importance
A33: LTI Ratio | B33: 0.35
A34: Credit History | B34: 0.35
A35: Employment Status | B35: 0.23
A36: Annual Income | B36: 0.05
A37: Age | B37: 0.02

Sheet Model Performance
A1: LOGISTIC REGRESSION — HOLD-OUT TEST PERFORMANCE
A2: 70/30 stratified split, random_state=42. Metrics are formulas on the Test rows of Credit Risk Data.
B4: Pred 0 | C4: Pred 1
A5: Actual 0 | B5: =COUNTIFS('Credit Risk Data'!$K$4:$K$203,"Test",'Credit Risk Data'!$H$4:$H$203,0,'Credit Risk Data'!$J$4:$J$203,0) -> 41 | C5: =COUNTIFS('Credit Risk Data'!$K$4:$K$203,"Test",'Credit Risk Data'!$H$4:$H$203,0,'Credit Risk Data'!$J$4:$J$203,1) -> 3
A6: Actual 1 | B6: =COUNTIFS('Credit Risk Data'!$K$4:$K$203,"Test",'Credit Risk Data'!$H$4:$H$203,1,'Credit Risk Data'!$J$4:$J$203,0) -> 1 | C6: =COUNTIFS('Credit Risk Data'!$K$4:$K$203,"Test",'Credit Risk Data'!$H$4:$H$203,1,'Credit Risk Data'!$J$4:$J$203,1) -> 15
A8: Metric | B8: Value | C8: Definition
A9: Test rows | B9: =SUM(B5:C6) -> 60 | C9: Hold-out records
A10: Accuracy | B10: =(B5+C6)/B9 -> 0.93333333 | C10: (TN+TP)/n
A11: Precision (default class) | B11: =C6/(C5+C6) -> 0.83333333 | C11: TP/(TP+FP)
A12: Recall (default class) | B12: =C6/(B6+C6) -> 0.9375 | C12: TP/(TP+FN)
A13: F1 score | B13: =2*B11*B12/(B11+B12) -> 0.88235294 | C13: Harmonic mean
A14: AUC-ROC | B14: 0.993 | C14: Computed in Python on the test rows
A16: MODEL COEFFICIENTS (raw scale — used by the demo’s Predict Borrower Risk tool)
A17: Term | B17: Coefficient
A18: Intercept | B18: -7.21692
A19: age | B19: -0.01363
A20: income_k | B20: -0.01449
A21: lti | B21: 4.33046
A22: credit_bad | B22: 4.03171
A23: credit_avg | B23: 2.01926
A24: emp_unemp | B24: 3.58045
A25: emp_self | B25: 0.42489
A27: logit = intercept + Σ coef × feature; P(default) = 1/(1+e^-logit). income_k = income in ₹ thousands; credit_bad/credit_avg and emp_unemp/emp_self are 0/1 dummies (Good, Employed = baseline).
A28: Caution: only 60 test records (16 defaults). Treat the metrics as indicative, not production-grade.

Sheet Portfolio
A1: LOAN PORTFOLIO — DERIVED FROM CREDIT DATASET
A2: Interest income and net P&L use the Assumptions rate; they are illustrative, not accounting results.
A3: Metric | B3: Value
A4: Loans in portfolio | B4: =COUNTA('Credit Risk Data'!A4:A203) -> 200
A5: Total disbursed (INR) | B5: =SUM('Credit Risk Data'!D4:D203) -> 8733027
A6: Defaults | B6: =SUM('Credit Risk Data'!H4:H203) -> 55
A7: Default rate (by count) | B7: =B6/B4 -> 0.275
A8: NPA exposure (INR) — principal of defaulted loans | B8: =SUMIF('Credit Risk Data'!H4:H203,1,'Credit Risk Data'!D4:D203) -> 3088982
A9: NPA % of disbursed | B9: =B8/B5 -> 0.35371264
A10: Interest income, 1 yr (INR) = disbursed × rate | B10: =B5*Assumptions!B10 -> 1047963.2
A11: Net P&L (INR) = interest income − NPA | B11: =B10-B8 -> -2041018.8
